passarg.py
passarg-0.1.0.dist-info/WHEEL
passarg-0.1.0.dist-info/METADATA
passarg-0.1.0.dist-info/RECORD
