Metadata-Version: 2.1
Name: passarg
Version: 0.1.0
Summary: OpenSSL-style password argument handling.
Author-email: Eugene Kim <ab@astral.blue>
Requires-Python: >=3.10,<4
Classifier: License :: OSI Approved :: MIT License
Project-URL: Homepage, https://github.com/astralblue/python-passarg
